CHANGES.txt
CONTRIBUTORS.txt
README.txt
bootstrap.py
buildout.cfg
setup.py
gocept/__init__.py
gocept.recipe.deploymentsandbox.egg-info/PKG-INFO
gocept.recipe.deploymentsandbox.egg-info/SOURCES.txt
gocept.recipe.deploymentsandbox.egg-info/dependency_links.txt
gocept.recipe.deploymentsandbox.egg-info/entry_points.txt
gocept.recipe.deploymentsandbox.egg-info/namespace_packages.txt
gocept.recipe.deploymentsandbox.egg-info/not-zip-safe
gocept.recipe.deploymentsandbox.egg-info/requires.txt
gocept.recipe.deploymentsandbox.egg-info/top_level.txt
gocept/recipe/__init__.py
gocept/recipe/deploymentsandbox/README.txt
gocept/recipe/deploymentsandbox/__init__.py
gocept/recipe/deploymentsandbox/tests/__init__.py
gocept/recipe/deploymentsandbox/tests/test_docs.py