Metadata-Version: 1.0
Name: gocept.recipe.deploymentsandbox
Version: 0.1.1
Summary: Setup a sandbox environment for deployments based on zc.recipe.deployment
Home-page: http://pypi.python.org/pypi/gocept.recipe.deploymentsandbox
Author: Christian Theune
Author-email: ct@gocept.com
License: ZPL
Platform: UNKNOWN
Classifier: Framework :: Buildout
Classifier: Intended Audience :: Developers
Classifier: Topic :: Software Development :: Build Tools
Classifier: Topic :: Software Development :: Libraries :: Python Modules
Classifier: License :: OSI Approved :: Zope Public License
